{
  "auditDate": "2025-11-06T20:49:04.986Z",
  "mode": "DRY_RUN",
  "phase1": {
    "indexesCreated": [],
    "indexesVerified": [
      "worker_text_search",
      "job_text_search"
    ],
    "textSearchResults": {
      "electrician": 2,
      "painting": 1
    }
  },
  "phase2": {
    "workersAudited": 20,
    "issuesFound": {
      "tradesMismatched": [],
      "invalidWorkTypes": [],
      "missingLocations": [
        {
          "_id": "6892b8f766a1e818f0c46151",
          "email": "kwame.asante1@kelmah.test"
        },
        {
          "_id": "6892b90166a1e818f0c46159",
          "email": "efua.mensah@kelmah.test"
        },
        {
          "_id": "6892b90b66a1e818f0c46161",
          "email": "kwaku.osei@kelmah.test"
        },
        {
          "_id": "6892f4816c0c9f13ca24e105",
          "email": "yaa.adjei@kelmah.test"
        },
        {
          "_id": "6892f4876c0c9f13ca24e109",
          "email": "fiifi.boateng@kelmah.test"
        },
        {
          "_id": "6892f48b6c0c9f13ca24e10d",
          "email": "afia.owusu@kelmah.test"
        },
        {
          "_id": "6892f48e6c0c9f13ca24e111",
          "email": "kwadwo.agyei@kelmah.test"
        },
        {
          "_id": "6892f4926c0c9f13ca24e115",
          "email": "esi.darko@kelmah.test"
        },
        {
          "_id": "6892f4966c0c9f13ca24e119",
          "email": "yaw.antwi@kelmah.test"
        },
        {
          "_id": "6892f49a6c0c9f13ca24e11d",
          "email": "adjoa.oppong@kelmah.test"
        },
        {
          "_id": "6892f49d6c0c9f13ca24e121",
          "email": "kwame.gyamfi@kelmah.test"
        },
        {
          "_id": "6892f4a16c0c9f13ca24e125",
          "email": "efua.acheampong@kelmah.test"
        },
        {
          "_id": "6892f4a56c0c9f13ca24e129",
          "email": "kwaku.addai@kelmah.test"
        },
        {
          "_id": "6892f4a96c0c9f13ca24e12d",
          "email": "yaa.wiredu@kelmah.test"
        },
        {
          "_id": "6892f4ad6c0c9f13ca24e131",
          "email": "fiifi.frimpong@kelmah.test"
        },
        {
          "_id": "6892f4b16c0c9f13ca24e135",
          "email": "afia.nyarko@kelmah.test"
        },
        {
          "_id": "6892f4b56c0c9f13ca24e139",
          "email": "kwadwo.bediako@kelmah.test"
        },
        {
          "_id": "6892f4b86c0c9f13ca24e13d",
          "email": "esi.appiah@kelmah.test"
        },
        {
          "_id": "6892f4bc6c0c9f13ca24e141",
          "email": "yaw.danso@kelmah.test"
        },
        {
          "_id": "6892f4c06c0c9f13ca24e145",
          "email": "adjoa.ofori@kelmah.test"
        }
      ],
      "ratingsOutOfRange": [],
      "invalidHourlyRates": [],
      "testDataRecords": [],
      "unstandardizedTrades": []
    },
    "actionsApplied": {
      "recordsDeleted": 0,
      "recordsUpdated": 0,
      "tradesStandardized": 0
    }
  },
  "phase3": {
    "jobsAudited": 6,
    "issuesFound": {
      "missingRequiredFields": [],
      "invalidBudgets": [],
      "missingCities": [
        {
          "_id": "68ba25116529c7cef511d248",
          "title": "Senior Electrical Engineer - Commercial Projects"
        },
        {
          "_id": "68ba25116529c7cef511d24a",
          "title": "Master Plumber - Residential & Commercial"
        },
        {
          "_id": "68ba25116529c7cef511d24c",
          "title": "Expert Carpenter - Custom Furniture Specialist"
        },
        {
          "_id": "68ba25116529c7cef511d24e",
          "title": "HVAC Technician - Climate Control Systems"
        },
        {
          "_id": "68ba25126529c7cef511d250",
          "title": "Construction Supervisor - Building Projects"
        },
        {
          "_id": "68ba25126529c7cef511d252",
          "title": "Professional Painter - Residential & Commercial"
        }
      ],
      "applicationCountIssues": [
        {
          "_id": "68ba25116529c7cef511d248",
          "title": "Senior Electrical Engineer - Commercial Projects",
          "count": null,
          "issue": "null"
        },
        {
          "_id": "68ba25116529c7cef511d24a",
          "title": "Master Plumber - Residential & Commercial",
          "count": null,
          "issue": "null"
        },
        {
          "_id": "68ba25116529c7cef511d24c",
          "title": "Expert Carpenter - Custom Furniture Specialist",
          "count": null,
          "issue": "null"
        },
        {
          "_id": "68ba25116529c7cef511d24e",
          "title": "HVAC Technician - Climate Control Systems",
          "count": null,
          "issue": "null"
        },
        {
          "_id": "68ba25126529c7cef511d250",
          "title": "Construction Supervisor - Building Projects",
          "count": null,
          "issue": "null"
        },
        {
          "_id": "68ba25126529c7cef511d252",
          "title": "Professional Painter - Residential & Commercial",
          "count": null,
          "issue": "null"
        }
      ],
      "duplicateJobs": [],
      "invalidStatuses": [
        {
          "_id": "68ba25116529c7cef511d248",
          "title": "Senior Electrical Engineer - Commercial Projects",
          "status": "open"
        },
        {
          "_id": "68ba25116529c7cef511d24a",
          "title": "Master Plumber - Residential & Commercial",
          "status": "open"
        },
        {
          "_id": "68ba25116529c7cef511d24c",
          "title": "Expert Carpenter - Custom Furniture Specialist",
          "status": "open"
        },
        {
          "_id": "68ba25116529c7cef511d24e",
          "title": "HVAC Technician - Climate Control Systems",
          "status": "open"
        },
        {
          "_id": "68ba25126529c7cef511d250",
          "title": "Construction Supervisor - Building Projects",
          "status": "open"
        },
        {
          "_id": "68ba25126529c7cef511d252",
          "title": "Professional Painter - Residential & Commercial",
          "status": "open"
        }
      ]
    },
    "actionsApplied": {
      "recordsDeleted": 0,
      "recordsUpdated": 0
    }
  },
  "phase4": {
    "testResults": {
      "textSearchWorkers": {
        "passed": true,
        "count": 2,
        "expected": "> 0"
      },
      "textSearchJobs": {
        "passed": true,
        "count": 1,
        "expected": "> 0"
      },
      "filterByTrade": {
        "passed": false,
        "count": 0,
        "expected": "> 0"
      },
      "filterByCity": {
        "passed": false,
        "count": 0,
        "expected": "> 0"
      },
      "combinedFilters": {
        "passed": true,
        "count": 0,
        "expected": "> 0"
      },
      "noDuplicates": {
        "passed": true,
        "message": "Total: 20, Unique: 20"
      },
      "noTestData": {
        "passed": true,
        "count": 0,
        "expected": 0
      }
    }
  },
  "phase5": {
    "summary": {
      "totalWorkersAudited": 20,
      "totalJobsAudited": 6,
      "totalIssuesFound": 38,
      "totalRecordsModified": 0,
      "testsPassedCount": 5,
      "totalTestsCount": 7,
      "testPassRate": "71%"
    },
    "searchAccuracyImprovement": "0%",
    "recommendations": [
      "CRITICAL: Complete trade standardization - exact match filtering broken",
      "Re-run audit with --apply flag to fix identified issues"
    ]
  }
}